Workbook

Sheet 兴远渠道计算
A1: 兴远国际线上渠道合集--ozon官方指定物流 | M1: 2026.07.17版 | P1: 填入重量/KG ↓ | Q1: 填入销售价值/卢布 ↓ | R1: 三边尺寸/CM（长*宽*高）↓
A2: 产品模式 | B2: 分类 | C2: 运输方式 | D2: 渠道名称 | E2: 价格 | F2: 广州到莫斯科分拣中心时效（天） | G2: 运费预估 | H2: 货值限制/卢布 | I2: 重量服务范围 | J2: 尺寸服务范围 | K2: 计重方式 | L2: 免费顺丰揽收标准 | M2: 渠道优势 | P2: 0.5 | Q2: 5000 | R2: 54 | S2: 54 | T2: 4
A3: rFbs | B3: Extra Small （标准超级轻小件） | C3: Economy 陆运 | D3: XY Economy Extra Small | E3: ¥3.37元+ ¥0.0281/克 | F3: 13-18天 | G3: =俄罗斯公式!H2 -> 货值超渠道限制 | H3: 不超1600卢布 | I3: 1克→550克 | J3: 单边≤60cm； 三边和（长+宽+高）≤90cm | K3: 按照实重计费 | L3: 50件或大于等于10KG | M3: 适合重量0.001-0.5KG、货值1500卢布以内的商品，推荐用于3C、小饰品等小件商品 | P3: 注意：选择退回中国需要提供退回中国的详细地址和联系电话
C4: Standard 陆空联运 | D4: XY Extra Small Standard | E4: ¥3.37元+ ¥0.0393/克 | F4: 10-15天 | G4: =俄罗斯公式!H4 -> 货值超渠道限制 | P4: 包裹已经在国外：「客户退件」: 即包裹已被买家签收不满意后需要处理的包裹
B5: Budget （标准低客单价） | C5: Economy 陆运 | D5: XY Economy Budget | E5: ¥25.83元+ ¥0.0191/1克 | F5: 13-18天 | G5: =俄罗斯公式!H8 -> 货值超渠道限制 | H5: 不超1600卢布 | I5: 551克→30千克 | J5: 单边≤60cm； 三边和（长+宽+高）≤150cm | M5: 适合产品货值较低但体积较大的商品 | P5: 包裹已经在国外：「买家未签收的包裹」: 即包裹未被买家签收不满意或未签收取消后需要处理的包裹
C6: Standard 陆空联运 | D6: XY Standard Budget | E6: ¥25.83元+ ¥0.0281/克 | F6: 10-15天 | G6: =俄罗斯公式!H10 -> 货值超渠道限制 | P6: 包裹在国内所有集货仓：「包裹问题件」: 即包裹在仓库入仓前出现问题的包裹
B7: Small （标准小件） | C7: Economy 陆运 | D7: XY Economy Small | E7: ¥17.97元+ ¥0.0281/克 | F7: 13-18天 | G7: =俄罗斯公式!H14 -> 32.02元 | H7: 1501→7200卢布 | I7: 1克→2200克 | J7: 单边≤60cm； 三边和（长+宽+高）≤150cm | M7: 适合重量2KG内，货值1501-7200卢布以内的商品 | P7: 包裹在国内/国外：「海关清关失败退回」: 即包裹在中俄海关清关失败的包裹
C8: Standard 陆空联运 | D8: XY Standard Small | E8: ¥17.97元+ ¥0.0393/克 | F8: 10-15天 | G8: =俄罗斯公式!H16 -> 37.62元 | P8: 说明 | Q8: 客户退件 （国外） | S8: 买家未签收的包裹 （国外） | U8: 包裹问题件 （国内集货仓） | V8: 海关退回
B9: Big （标准大件） | C9: Economy 陆运 | D9: XY Economy Big | E9: ¥40.44元+ ¥0.0191/1克 | F9: 13-18天 | G9: =俄罗斯公式!H20 -> 重量限制2201G | H9: 1501→7200卢布 | I9: 2201克→30千克 | J9: 单边≤150cm； 三边和（长+宽+高）≤310cm | K9: 实重vs体积重混合计费 （公式：长×宽×高/12000） | M9: 适合重量在2KG-30KG之间、货值在1500-7200卢布以内的商品 | P9: 存储时间 | Q9: 免费存储14天，14天内没收到准确的处理方案，处理进行销毁 | S9: 免费存储7天 8-14天存储费3元/件/天 第15天销毁 | U9: 7天未提供方案进行销毁 | V9: 中国口岸/俄罗斯清关失败，监管仓退回： 支付1.5倍运费
C10: Standard 陆空联运 | D10: XY Standard Big | E10: ¥40.44元+ ¥0.0281/克 | F10: 10-15天 | G10: =俄罗斯公式!H22 -> 重量限制2201G | P10: 费用价格 | Q10: 中国发出到俄罗斯运费的1.5倍 （负责从俄罗斯退回到边境仓后，德邦快递到付到买家手里）
B11: Premium Small （高客单价小件） | C11: Economy 陆运 | D11: XY Economy Premium Small | E11: ¥24.71元+ ¥0.0281/克 | F11: 13-18天 | G11: =俄罗斯公式!H26 -> 货值小于渠道限制 | H11: 7001→250000卢布 | I11: 1克→5500克 | J11: 单边≤150cm； 三边和（长+宽+高）≤250cm | K11: 按照实重计费 | M11: 适合重量0.001-5KG，专门针对重量5KG以内的高客单价商品，提供高性价比选择
C12: Standard 陆空联运 | D12: XY Standard Premium Small | E12: ¥24.71元+ ¥0.0393/克 | F12: 10-15天 | G12: =俄罗斯公式!H28 -> 货值小于渠道限制 | P12: 以上政策将根据最新计算器版本政策为准
B13: Premium Big （高客单价大件） | C13: Economy 陆运 | D13: XY Economy Premium Big | E13: ¥69.64元+ ¥0.0258/克 | F13: 13-18天 | G13: =俄罗斯公式!H32 -> 货值小于渠道限制 | H13: 7001→250000卢布 | I13: 5501克→30千克 | J13: 单边≤150cm； 三边和（长+宽+高）≤310cm | K13: 实重vs体积重混合计费 （公式：长×宽×高/12000） | M13: 针对5-30kg大件、7000-250000卢布的商品，提供最佳优质选择
C14: Standard 陆空联运 | D14: XY Standard Premium Big | E14: ¥69.64元+0.0314/克 | F14: 10-15天 | G14: =俄罗斯公式!H34 -> 货值小于渠道限制
B15: 中国邮政 （Eub特惠） | D15: ePacket Economy Track | E15: 12元+0.03元/克 | F15: 25-30天 | H15: 不超1000元人民币 | I15: 1克→5千克 | J15: 单边≤60cm； 三边和（长+宽+高）≤90cm | L15: 自送 | M15: 适合重量5KG内，货值1000人民币以内无时效要求的商品
B16: 中国邮政 （哈萨克斯坦） | D16: China Post ePacket Economy Track CIS | E16: 1.6元+0.033元/克 | F16: 15-20天
B17: 中国邮政 （白俄罗斯） | D17: China Post ePacket Economy Belarus | E17: 13元+0.03元/克 | F17: 20-30天 | M17: 适合重量5KG内无时效要求的商品
A18: 说明： 1、在使用过程中，在右上角输入完整的【重量+销售价值+尺寸】即可快捷查询费用； 2、运费预估会自动计算费用，同时计算的费用会按照【黄色背景标记】，如未有标记的为产品限制，可以查看限制原因； 3、该rFBS渠道合集文件归属兴远国际物流所有；以上价格仅供参考，如有实际变动请咨询群内专属客服获取最新。 | G18: 兴远国际主要服务分别有： WMS仓储闭环管理、中亚多仓布局、签收失败处理方案、 催促买家取货服务、一件直发/代发增值服务、俄语客服团队、中国专属客服、解决账单混乱、 多种干线运输等，全方位帮您解决物流问题。另外还提供一站式闭环物流服务【FBO】，包括海外仓头程运输、海外仓配套服务、海外仓最后一公里配送到门/到点。更有推荐新客户有礼活动，超高福利机制等你哦！ 揽收地址 *【代贴单寄货地址】​ 姓名:张伟杰 地区:山东省 临沂市 兰山区 详细地址:五路与顺和街交汇顺和母幼采购基地东门沿街（1026店内）送货上门（请填写您的客户编码+备注已贴单/代贴单+拆包/不拆包） 电话：15963336383 *【已贴单寄货地址】 地区:山东省 临沂市 兰山区 详细地址:五路与顺和街交汇顺和母幼采购基地东门沿街（1026店内）送货上门（请填写您的客户编码+备注已贴单/代贴单+拆包/不拆包） 联系人：张伟杰 电话：15963336383
A19: 选择兴远国际——让跨境运输跟简单！◆自有清关公司，通关畅通无阻◆自有陆运公司，保证运输时效◆边境/保税仓库，灵活运输方式◆自主研发系统，客户操作便捷◆智能分拣设备，数据精准高效◆内部智能管理，客户满意度高

Sheet 兴远吉尔吉斯渠道计算
A1: 兴远国际线上渠道合集--ozon官方指定物流 | L1: 2026.07.17版 | O1: 填入重量/KG ↓ | P1: 填入销售价值/卢布 ↓ | Q1: 三边尺寸/CM（长*宽*高）↓
A2: 产品模式 | B2: 分类 | C2: 运输方式 | D2: 渠道名称 | E2: 价格 | F2: 广州到莫斯科分拣中心时效（天） | G2: 运费预估 | H2: 货值限制/卢布 | I2: 重量服务范围 | J2: 尺寸服务范围 | K2: 计重方式 | L2: 渠道优势 | O2: 0 | P2: 0 | Q2: 0 | R2: 0 | S2: 0
A3: rFbs | B3: Extra Small （标准超级轻小件） | C3: Standard 陆空联运 | D3: Xingyuan Kyrgysztan Standard Extra Small | E3: ¥3,37+¥0,0393/g | F3: 30-35天 | G3: =吉尔吉斯公式!H4 -> 请检查重量 | H3: 不超1600卢布 | I3: 1克→500克 | J3: 单边≤60cm； 三边和（长+宽+高）≤90cm | K3: 按照实重计费 | L3: 适合重量0.001-0.5KG、货值1500卢布以内的商品，推荐用于3C、小饰品等小件商品
B4: Budget （标准低客单价） | C4: Standard 陆空联运 | D4: Xingyuan Kyrgysztan Standard Budget | E4: ¥23,83+¥0,0281/g | F4: 30-35天 | G4: =吉尔吉斯公式!H10 -> 请检查重量 | H4: 不超1600卢布 | I4: 501克→30千克 | J4: 单边≤60cm； 三边和（长+宽+高）≤150cm | L4: 适合产品货值较低但体积较大的商品
B5: Small （标准小件） | C5: Standard 陆空联运 | D5: Xingyuan Kyrgysztan Standard Small | E5: ¥17,97+¥0,0393/g | F5: 30-35天 | G5: =吉尔吉斯公式!H16 -> 请检查重量 | H5: 1501→7200卢布 | I5: 1克→2000克 | J5: 单边≤60cm； 三边和（长+宽+高）≤150cm | L5: 适合重量2KG内，货值1501-7200卢布以内的商品
B6: Big （标准大件） | C6: Standard 陆空联运 | D6: Xingyuan Kyrgysztan Standard Big | E6: ¥40,44+¥0,0281/g | F6: 30-35天 | G6: =吉尔吉斯公式!H22 -> 请检查重量 | H6: 1501→7200卢布 | I6: 2001克→30千克 | J6: 单边≤150cm； 三边和（长+宽+高）≤310cm | K6: 实重vs体积重混合计费 （公式：长×宽×高/12000） | L6: 适合重量在2KG-30KG之间、货值在1500-7200卢布以内的商品
B7: Premium Small （高客单价小件） | C7: Standard 陆空联运 | D7: Xingyuan Kyrgysztan Standard Premium Small | E7: ¥24,71+¥0,0393/g | F7: 30-35天 | G7: =吉尔吉斯公式!H28 -> 请检查重量 | H7: 7001→18000卢布 | I7: 1克→5000克 | J7: 单边≤150cm； 三边和（长+宽+高）≤250cm | K7: 按照实重计费 | L7: 适合重量0.001-5KG，专门针对重量5KG以内的高客单价商品，提供高性价比选择
B8: Premium Big （高客单价大件） | C8: Standard 陆空联运 | D8: Xingyuan Kyrgysztan Standard Premium Big | E8: ¥69,64+¥0,0314/g | F8: 30-35天 | G8: =吉尔吉斯公式!H34 -> 请检查重量 | H8: 7001→18000卢布 | I8: 5001克→30千克 | J8: 单边≤150cm； 三边和（长+宽+高）≤310cm | K8: 实重vs体积重混合计费 （公式：长×宽×高/12000） | L8: 针对5-30kg大件、7000-250000卢布的商品，提供最佳优质选择
B9: 中国邮政 （Eub特惠） | D9: ePacket Economy Track | E9: 12元+0.03元/克 | F9: 25-30天 | H9: 不超1000元人民币 | I9: 1克→5千克 | J9: 单边≤60cm； 三边和（长+宽+高）≤90cm | L9: 适合重量5KG内，货值1000人民币以内无时效要求的商品
B10: 中国邮政 （哈萨克斯坦） | D10: China Post ePacket Economy Track CIS | E10: 1.6元+0.033元/克 | F10: 15-20天
B11: 中国邮政 （白俄罗斯） | D11: China Post ePacket Economy Belarus | E11: 13元+0.03元/克 | F11: 20-30天 | L11: 适合重量5KG内无时效要求的商品
A12: 说明： 1、在使用过程中，在右上角输入完整的【重量+销售价值+尺寸】即可快捷查询费用； 2、运费预估会自动计算费用，同时计算的费用会按照【黄色背景标记】，如未有标记的为产品限制，可以查看限制原因； 3、该rFBS渠道合集文件归属兴远国际物流所有；以上价格仅供参考，如有实际变动请咨询群内专属客服获取最新。 | G12: 兴远国际主要服务分别有： 顺丰全国免费上门揽收服务、WMS仓储闭环管理、中亚多仓布局、签收失败处理方案、 催促买家取货服务、一件直发/代发增值服务、俄语客服团队、中国专属客服、解决账单混乱、 多种干线运输等，全方位帮您解决物流问题。另外还提供一站式闭环物流服务【FBO】，包括海外仓头程运输、海外仓配套服务、海外仓最后一公里配送到门/到点。更有推荐新客户有礼活动，超高福利机制等你哦！ 兴远广州仓库： 收件人：已贴单/代贴单 电话：18127985337 广州仓地址：广州市白云区鹤边鹤龙二横路3号B127档OZON官方物流兴远国际（您的客户编码） 【工作时间】周一至周六，上午9：00至晚上22:30 周日，上午9:00至下午18:30
A13: 选择兴远国际——让跨境运输跟简单！◆自有清关公司，通关畅通无阻◆自有陆运公司，保证运输时效◆边境/保税仓库，灵活运输方式◆自主研发系统，客户操作便捷◆智能分拣设备，数据精准高效◆内部智能管理，客户满意度高

Sheet 俄罗斯公式
A1: 分类 | B1: 运输方式 | C1: 渠道名称 | D1: 到取货点/到门 | E1: 价格 | F1: 运费 | G1: 挂号费 | H1: 价格 | J1: 填入重量/KG ↓ | K1: 填入销售价值/卢布 ↓ | L1: 三边尺寸/CM（长*宽*高）↓ | P1: 三边之和 | Q1: 重量判断 (3位小数） | S1: 三边判断是否超90cm | T1: =IF($P$2>=90,"三边合计超长","正常") -> 三边合计超长 | V1: 单边判断是否超60cm | W1: {=IF(OR($L$2:$N$2>60),"单边超长","正常")} -> 正常
A2: Extra Small （标准超级轻小件） | B2: Economy | C2: XY Economy Extra Small | D2: 到取货点 （PUDO） | E2: ¥3.37元+ ¥0.0281/克 | F2: 28.1 | G2: 3.37 | H2: =IF($Q$2<=0,"请检查重量",IF($K$2>1600,"货值超渠道限制",IF($Q$2>0.55,"重量限制550G",IF($T$1="三边合计超长","三边合计超长",IF($W$1="单边超长","单边超长",ROUNDUP(F2*$Q$2+G2,2)&"元"))))) -> 货值超渠道限制 | J2: =兴远渠道计算!P2 -> 0.5 | K2: =兴远渠道计算!Q2 -> 5000 | L2: =兴远渠道计算!R2 -> 54 | M2: =兴远渠道计算!S2 -> 54 | N2: =兴远渠道计算!T2 -> 4 | P2: =SUM(L2:N2) -> 112 | Q2: =IF($J$2<=0,0,CEILING($J$2,0.001)) -> 0.5 | S2: 三边判断是否超150cm | T2: =IF($P$2>=150,"三边合计超长","正常") -> 正常 | V2: 单边判断是否超150cm | W2: {=IF(OR($L$2:$N$2>150),"单边超长","正常")} -> 正常
B3: Economy | C3: XY Economy Extra Small | D3: 到门 （Courier） | E3: ¥3.37元+ ¥0.0281/克 | F3: 28.1 | G3: 3.37 | H3: =IF($Q$2<=0,"请检查重量",IF($K$2>1600,"货值超渠道限制",IF($Q$2>0.55,"重量限制550G",IF($T$1="三边合计超长","三边合计超长",IF($W$1="单边超长","单边超长",ROUNDUP(F3*$Q$2+G3,2)&"元"))))) -> 货值超渠道限制 | S3: 三边判断是否超250cm | T3: =IF($P$2>=250,"三边合计超长","正常") -> 正常
B4: Standard | C4: XY Extra Small Standard | D4: 到取货点 （PUDO） | E4: ¥3.37元+ ¥0.0393/克 | F4: 39.3 | G4: 3.37 | H4: =IF($Q$2<=0,"请检查重量",IF($K$2>1600,"货值超渠道限制",IF($Q$2>0.55,"重量限制550G",IF($T$1="三边合计超长","三边合计超长",IF($W$1="单边超长","单边超长",ROUNDUP(F4*$Q$2+G4,2)&"元"))))) -> 货值超渠道限制 | S4: 三边判断是否超310cm | T4: =IF($P$2>=310,"三边合计超长","正常") -> 正常
B5: Standard | C5: XY Extra Small Standard | D5: 到门 （Courier） | E5: ¥3.37元+ ¥0.0393/克 | F5: 39.3 | G5: 3.37 | H5: =IF($Q$2<=0,"请检查重量",IF($K$2>1600,"货值超渠道限制",IF($Q$2>0.55,"重量限制550G",IF($T$1="三边合计超长","三边合计超长",IF($W$1="单边超长","单边超长",ROUNDUP(F5*$Q$2+G5,2)&"元"))))) -> 货值超渠道限制 | V5: 计抛渠道对比（计抛） | W5: =IF($L$2*$M$2*$N$2/12000>$Q$2,$L$2*$M$2*$N$2/12000,$Q$2) -> 0.972
B6: Express | C6: XY Express Extra Small | D6: 到取货点 （PUDO） | E6: ¥3元+ ¥0.045/克 | F6: 45 | G6: 3.12 | H6: =IF($Q$2<=0,"请检查重量",IF($K$2>1600,"货值超渠道限制",IF($Q$2>0.5,"重量限制500G",IF($T$1="三边合计超长","三边合计超长",IF($W$1="单边超长","单边超长",ROUNDUP(F6*$Q$2+G6,2)&"元"))))) -> 货值超渠道限制
B7: Express | C7: XY Express Extra Small | D7: 到门 （Courier） | E7: ¥3元+ ¥0.045/克 | F7: 45 | G7: 3.12 | H7: =IF($Q$2<=0,"请检查重量",IF($K$2>1600,"货值超渠道限制",IF($Q$2>0.5,"重量限制500G",IF($T$1="三边合计超长","三边合计超长",IF($W$1="单边超长","单边超长",ROUNDUP(F7*$Q$2+G7,2)&"元"))))) -> 货值超渠道限制
A8: Budget （标准低客单价） | B8: Economy | C8: XY Economy Budget （新） | D8: 到取货点 （PUDO） | E8: ¥25.83元+ ¥0.0191/1克 | F8: 19.1 | G8: 25.83 | H8: =IF($Q$2<=0,"请检查重量",IF($K$2>1600,"货值超渠道限制",IF($Q$2>30,"重量限制30KG",IF($Q$2<0.551,"重量不能低于551克",IF($T$2="三边合计超长","三边合计超长",IF($W$1="单边超长","单边超长",ROUNDUP(F8*$Q$2+G8,2)&"元")))))) -> 货值超渠道限制
B9: Economy | C9: XY Economy Budget （新） | D9: 到门 （Courier） | E9: ¥25.83元+ ¥0.0191/1克 | F9: 19.1 | G9: 25.83 | H9: =IF($Q$2<=0,"请检查重量",IF($K$2>1600,"货值超渠道限制",IF($Q$2>30,"重量限制30KG",IF($Q$2<0.551,"重量不能低于551克",IF($T$2="三边合计超长","三边合计超长",IF($W$1="单边超长","单边超长",ROUNDUP(F9*$Q$2+G9,2)&"元")))))) -> 货值超渠道限制
B10: Standard | C10: XY Standard Budget | D10: 到取货点 （PUDO） | E10: ¥25.83元+ ¥0.0281/克 | F10: 28.1 | G10: 25.83 | H10: =IF($Q$2<=0,"请检查重量",IF($K$2>1600,"货值超渠道限制",IF($Q$2>30,"重量限制30KG",IF($Q$2<0.551,"重量不能低于551克",IF($T$2="三边合计超长","三边合计超长",IF($W$1="单边超长","单边超长",ROUNDUP(F10*$Q$2+G10,2)&"元")))))) -> 货值超渠道限制
B11: Standard | C11: XY Standard Budget | D11: 到门 （Courier） | E11: ¥25.83元+ ¥0.0281/克 | F11: 28.1 | G11: 25.83 | H11: =IF($Q$2<=0,"请检查重量",IF($K$2>1600,"货值超渠道限制",IF($Q$2>30,"重量限制30KG",IF($Q$2<0.551,"重量不能低于551克",IF($T$2="三边合计超长","三边合计超长",IF($W$1="单边超长","单边超长",ROUNDUP(F11*$Q$2+G11,2)&"元")))))) -> 货值超渠道限制
B12: Express | C12: XY Express Budget （新） | D12: 到取货点 （PUDO） | E12: ¥23元+ ¥0.033/1克 | F12: 33 | G12: 23.92 | H12: =IF($Q$2<=0,"请检查重量",IF($K$2>1600,"货值超渠道限制",IF($Q$2>30,"重量限制30KG",IF($Q$2<0.501,"重量不能低于501克",IF($T$2="三边合计超长","三边合计超长",IF($W$1="单边超长","单边超长",ROUNDUP(F12*$Q$2+G12,2)&"元")))))) -> 货值超渠道限制
B13: Express | C13: XY Express Budget （新） | D13: 到门 （Courier） | E13: ¥23元+ ¥0.033/1克 | F13: 33 | G13: 23.92 | H13: =IF($Q$2<=0,"请检查重量",IF($K$2>1600,"货值超渠道限制",IF($Q$2>30,"重量限制30KG",IF($Q$2<0.501,"重量不能低于501克",IF($T$2="三边合计超长","三边合计超长",IF($W$1="单边超长","单边超长",ROUNDUP(F13*$Q$2+G13,2)&"元")))))) -> 货值超渠道限制
A14: Small （标准小件） | B14: Economy | C14: XY Economy Small | D14: 到取货点 （PUDO） | E14: ¥17.97元+ ¥0.0281/克 | F14: 28.1 | G14: 17.97 | H14: =IF($Q$2<=0,"请检查重量",IF($K$2<1501,"货值小于渠道限制",IF($K$2>7200,"货值超渠道限制",IF($Q$2>2.2,"重量限制2.2KG",IF($T$2="三边合计超长","三边合计超长",IF($W$1="单边超长","单边超长",ROUNDUP(F14*$Q$2+G14,2)&"元")))))) -> 32.02元
B15: Economy | C15: XY Economy Small | D15: 到门 （Courier） | E15: ¥17.97元+ ¥0.0281/克 | F15: 28.1 | G15: 17.97 | H15: =IF($Q$2<=0,"请检查重量",IF($K$2<1501,"货值小于渠道限制",IF($K$2>7200,"货值超渠道限制",IF($Q$2>2.2,"重量限制2.2KG",IF($T$2="三边合计超长","三边合计超长",IF($W$1="单边超长","单边超长",ROUNDUP(F15*$Q$2+G15,2)&"元")))))) -> 32.02元
B16: Standard | C16: XY Standard Small | D16: 到取货点 （PUDO） | E16: ¥17.97元+ ¥0.0393/克 | F16: 39.3 | G16: 17.97 | H16: =IF($Q$2<=0,"请检查重量",IF($K$2<1501,"货值小于渠道限制",IF($K$2>7200,"货值超渠道限制",IF($Q$2>2.2,"重量限制2.2KG",IF($T$2="三边合计超长","三边合计超长",IF($W$1="单边超长","单边超长",ROUNDUP(F16*$Q$2+G16,2)&"元")))))) -> 37.62元
B17: Standard | C17: XY Standard Small | D17: 到门 （Courier） | E17: ¥17.97元+ ¥0.0393/克 | F17: 39.3 | G17: 17.97 | H17: =IF($Q$2<=0,"请检查重量",IF($K$2<1501,"货值小于渠道限制",IF($K$2>7200,"货值超渠道限制",IF($Q$2>2.2,"重量限制2.2KG",IF($T$2="三边合计超长","三边合计超长",IF($W$1="单边超长","单边超长",ROUNDUP(F17*$Q$2+G17,2)&"元")))))) -> 37.62元
B18: Express | C18: XY Express Small | D18: 到取货点 （PUDO） | E18: ¥16元+ ¥0.045/克 | F18: 16 | G18: 16.64 | H18: =IF($Q$2<=0,"请检查重量",IF($K$2<1501,"货值小于渠道限制",IF($K$2>7200,"货值超渠道限制",IF($Q$2>2,"重量限制2KG",IF($T$2="三边合计超长","三边合计超长",IF($W$1="单边超长","单边超长",ROUNDUP(F18*$Q$2+G18,2)&"元")))))) -> 24.64元
B19: Express | C19: XY Express Small | D19: 到门 （Courier） | E19: ¥16元+ ¥0.045/克 | F19: 16 | G19: 16.64 | H19: =IF($Q$2<=0,"请检查重量",IF($K$2<1501,"货值小于渠道限制",IF($K$2>7200,"货值超渠道限制",IF($Q$2>2,"重量限制2KG",IF($T$2="三边合计超长","三边合计超长",IF($W$1="单边超长","单边超长",ROUNDUP(F19*$Q$2+G19,2)&"元")))))) -> 24.64元
A20: Big （标准大件） | B20: Economy | C20: XY Economy Big （新） | D20: 到取货点 （PUDO） | E20: ¥40.44元+ ¥0.0191/1克 | F20: 19.1 | G20: 40.44 | H20: =IF($Q$2<=0,"请检查重量",IF($K$2<1501,"货值小于渠道限制",IF($K$2>7200,"货值超渠道限制",IF($Q$2<2.201,"重量限制2201G",IF($Q$2>30,"重量限制30KG",IF($W$5>30,"体积重超30KG",IF($T$3="三边合计超长","三边合计超长",IF($W$2="单边超长","单边超长",ROUNDUP(F20*$W$5+G20,2)&"元")))))))) -> 重量限制2201G
B21: Economy | C21: XY Economy Big （新） | D21: 到门 （Courier） | E21: ¥40.44元+ ¥0.0191/1克 | F21: 19.1 | G21: 40.44 | H21: =IF($Q$2<=0,"请检查重量",IF($K$2<1501,"货值小于渠道限制",IF($K$2>7200,"货值超渠道限制",IF($Q$2<2.201,"重量限制2201G",IF($Q$2>30,"重量限制30KG",IF($W$5>30,"体积重超30KG",IF($T$3="三边合计超长","三边合计超长",IF($W$2="单边超长","单边超长",ROUNDUP(F21*$W$5+G21,2)&"元")))))))) -> 重量限制2201G
B22: Standard | C22: XY Standard Big | D22: 到取货点 （PUDO） | E22: ¥40.44元+ ¥0.0281/克 | F22: 28.1 | G22: 40.44 | H22: =IF($Q$2<=0,"请检查重量",IF($K$2<1501,"货值小于渠道限制",IF($K$2>7200,"货值超渠道限制",IF($Q$2<2.201,"重量限制2201G",IF($Q$2>30,"重量限制30KG",IF($W$5>30,"体积重超30KG",IF($T$3="三边合计超长","三边合计超长",IF($W$2="单边超长","单边超长",ROUNDUP(F22*$W$5+G22,2)&"元")))))))) -> 重量限制2201G
B23: Standard | C23: XY Standard Big | D23: 到门 （Courier） | E23: ¥40.44元+ ¥0.0281/克 | F23: 28.1 | G23: 40.44 | H23: =IF($Q$2<=0,"请检查重量",IF($K$2<1501,"货值小于渠道限制",IF($K$2>7200,"货值超渠道限制",IF($Q$2<2.201,"重量限制2201G",IF($Q$2>30,"重量限制30KG",IF($W$5>30,"体积重超30KG",IF($T$3="三边合计超长","三边合计超长",IF($W$2="单边超长","单边超长",ROUNDUP(F23*$W$5+G23,2)&"元")))))))) -> 重量限制2201G
B24: Express | C24: XY Express Big （新） | D24: 到取货点 （PUDO） | E24: ¥36元+ ¥0.033/1克 | F24: 33 | G24: 37.44 | H24: =IF($Q$2<=0,"请检查重量",IF($K$2<1501,"货值小于渠道限制",IF($K$2>7200,"货值超渠道限制",IF($Q$2<2.001,"重量限制2001G",IF($Q$2>30,"重量限制30KG",IF($W$5>30,"体积重超30KG",IF($T$3="三边合计超长","三边合计超长",IF($W$2="单边超长","单边超长",ROUNDUP(F24*$W$5+G24,2)&"元")))))))) -> 重量限制2001G
B25: Express | C25: XY Express Big （新） | D25: 到门 （Courier） | E25: ¥36元+ ¥0.033/1克 | F25: 33 | G25: 37.44 | H25: =IF($Q$2<=0,"请检查重量",IF($K$2<1501,"货值小于渠道限制",IF($K$2>7200,"货值超渠道限制",IF($Q$2<2.001,"重量限制2001G",IF($Q$2>30,"重量限制30KG",IF($W$5>30,"体积重超30KG",IF($T$3="三边合计超长","三边合计超长",IF($W$2="单边超长","单边超长",ROUNDUP(F25*$W$5+G25,2)&"元")))))))) -> 重量限制2001G
A26: XY Premium Small （高客单价小件） | B26: Economy | C26: XY Economy Premium Small | D26: 到取货点 （PUDO） | E26: ¥24.71元+ ¥0.0281/克 | F26: 28.1 | G26: 24.71 | H26: =IF($Q$2<=0,"请检查重量",IF($K$2<7000,"货值小于渠道限制",IF($K$2>250000,"货值超渠道限制",IF($Q$2>5.5,"重量限制5.5KG",IF($T$3="三边合计超长","三边合计超长",IF($W$2="单边超长","单边超长",ROUNDUP(F26*$Q$2+G26,2)&"元")))))) -> 货值小于渠道限制
B27: Economy | C27: XY Economy Premium Small | D27: 到门 （Courier） | E27: ¥24.71元+ ¥0.0281/克 | F27: 28.1 | G27: 24.71 | H27: =IF($Q$2<=0,"请检查重量",IF($K$2<7000,"货值小于渠道限制",IF($K$2>250000,"货值超渠道限制",IF($Q$2>5.5,"重量限制5.5KG",IF($T$3="三边合计超长","三边合计超长",IF($W$2="单边超长","单边超长",ROUNDUP(F27*$Q$2+G27,2)&"元")))))) -> 货值小于渠道限制
B28: Standard | C28: XY Standard Premium Small | D28: 到取货点 （PUDO） | E28: ¥24.71元+ ¥0.0393/克 | F28: 39.3 | G28: 24.71 | H28: =IF($Q$2<=0,"请检查重量",IF($K$2<7000,"货值小于渠道限制",IF($K$2>250000,"货值超渠道限制",IF($Q$2>5.5,"重量限制5.5KG",IF($T$3="三边合计超长","三边合计超长",IF($W$2="单边超长","单边超长",ROUNDUP(F28*$Q$2+G28,2)&"元")))))) -> 货值小于渠道限制
B29: Standard | C29: XY Standard Premium Small | D29: 到门 （Courier） | E29: ¥24.71元+ ¥0.0393/克 | F29: 39.3 | G29: 24.71 | H29: =IF($Q$2<=0,"请检查重量",IF($K$2<7000,"货值小于渠道限制",IF($K$2>250000,"货值超渠道限制",IF($Q$2>5.5,"重量限制5.5KG",IF($T$3="三边合计超长","三边合计超长",IF($W$2="单边超长","单边超长",ROUNDUP(F29*$Q$2+G29,2)&"元")))))) -> 货值小于渠道限制
B30: Express | C30: XY Express Premium Small | D30: 到取货点 （PUDO） | E30: ¥22元+ ¥0.045/克 | F30: 26 | G30: 22.88 | H30: =IF($Q$2<=0,"请检查重量",IF($K$2<7000,"货值小于渠道限制",IF($K$2>250000,"货值超渠道限制",IF($Q$2>5,"重量限制5KG",IF($T$3="三边合计超长","三边合计超长",IF($W$2="单边超长","单边超长",ROUNDUP(F30*$Q$2+G30,2)&"元")))))) -> 货值小于渠道限制
B31: Express | C31: XY Express Premium Small | D31: 到门 （Courier） | E31: ¥22元+ ¥0.045/克 | F31: 26 | G31: 22.88 | H31: =IF($Q$2<=0,"请检查重量",IF($K$2<7000,"货值小于渠道限制",IF($K$2>250000,"货值超渠道限制",IF($Q$2>5,"重量限制5KG",IF($T$3="三边合计超长","三边合计超长",IF($W$2="单边超长","单边超长",ROUNDUP(F31*$Q$2+G31,2)&"元")))))) -> 货值小于渠道限制
A32: Premium Big （高客单价大件） | B32: Economy | C32: XY Economy Premium Big （新） | D32: 到取货点 （PUDO） | E32: ¥69.64元+ ¥0.0258/克 | F32: 25.8 | G32: 69.64 | H32: =IF($Q$2<=0,"请检查重量",IF($K$2<7000,"货值小于渠道限制",IF($K$2>250000,"货值超渠道限制",IF($Q$2<5.501,"最低限制5501G",IF($Q$2>30,"重量限制30KG",IF($W$5>30,"体积重超30KG",IF($T$4="三边合计超长","三边合计超长",IF($W$2="单边超长","单边超长",ROUNDUP(F32*$W$5+G32,2)&"元")))))))) -> 货值小于渠道限制
B33: Economy | C33: XY Economy Premium Big （新） | D33: 到门 （Courier） | E33: ¥69.64元+ ¥0.0258/克 | F33: 25.8 | G33: 69.64 | H33: =IF($Q$2<=0,"请检查重量",IF($K$2<7000,"货值小于渠道限制",IF($K$2>250000,"货值超渠道限制",IF($Q$2<5.501,"最低限制5501G",IF($Q$2>30,"重量限制30KG",IF($W$5>30,"体积重超30KG",IF($T$4="三边合计超长","三边合计超长",IF($W$2="单边超长","单边超长",ROUNDUP(F33*$W$5+G33,2)&"元")))))))) -> 货值小于渠道限制
B34: Standard | C34: XY Standard Premium Big | D34: 到取货点 （PUDO） | E34: ¥69.64元+0.0314/克 | F34: 31.4 | G34: 69.64 | H34: =IF($Q$2<=0,"请检查重量",IF($K$2<7000,"货值小于渠道限制",IF($K$2>250000,"货值超渠道限制",IF($Q$2<5.501,"最低限制5501G",IF($Q$2>30,"重量限制30KG",IF($W$5>30,"体积重超30KG",IF($T$4="三边合计超长","三边合计超长",IF($W$2="单边超长","单边超长",ROUNDUP(F34*$W$5+G34,2)&"元")))))))) -> 货值小于渠道限制
B35: Standard | C35: XY Standard Premium Big | D35: 到门 （Courier） | E35: ¥69.64元+0.0314/克 | F35: 31.4 | G35: 69.64 | H35: =IF($Q$2<=0,"请检查重量",IF($K$2<7000,"货值小于渠道限制",IF($K$2>250000,"货值超渠道限制",IF($Q$2<5.501,"最低限制5501G",IF($Q$2>30,"重量限制30KG",IF($W$5>30,"体积重超30KG",IF($T$4="三边合计超长","三边合计超长",IF($W$2="单边超长","单边超长",ROUNDUP(F35*$W$5+G35,2)&"元")))))))) -> 货值小于渠道限制
B36: Express | C36: XY Express Premium Big （新） | D36: 到取货点 （PUDO） | E36: ¥62元+ ¥0.033/1克 | F36: 33 | G36: 64.48 | H36: =IF($Q$2<=0,"请检查重量",IF($K$2<7000,"货值小于渠道限制",IF($K$2>250000,"货值超渠道限制",IF($Q$2<5.001,"最低限制5001G",IF($Q$2>30,"重量限制30KG",IF($W$5>30,"体积重超30KG",IF($T$4="三边合计超长","三边合计超长",IF($W$2="单边超长","单边超长",ROUNDUP(F36*$W$5+G36,2)&"元")))))))) -> 货值小于渠道限制
B37: Express | C37: XY Express Premium Big （新） | D37: 到门 （Courier） | E37: ¥62元+ ¥0.033/1克 | F37: 33 | G37: 64.48 | H37: =IF($Q$2<=0,"请检查重量",IF($K$2<7000,"货值小于渠道限制",IF($K$2>250000,"货值超渠道限制",IF($Q$2<5.001,"最低限制5001G",IF($Q$2>30,"重量限制30KG",IF($W$5>30,"体积重超30KG",IF($T$4="三边合计超长","三边合计超长",IF($W$2="单边超长","单边超长",ROUNDUP(F37*$W$5+G37,2)&"元")))))))) -> 货值小于渠道限制

Sheet 吉尔吉斯公式
A1: 分类 | B1: 运输方式 | C1: 渠道名称 | D1: 到取货点/到门 | E1: 价格 | F1: 运费 | G1: 挂号费 | H1: 价格 | J1: 填入重量/KG ↓ | K1: 填入销售价值/卢布 ↓ | L1: 三边尺寸/CM（长*宽*高）↓ | P1: 三边之和 | Q1: 重量判断 (3位小数） | S1: 三边判断是否超90cm | T1: =IF($P$2>=90,"三边合计超长","正常") -> 正常 | V1: 单边判断是否超60cm | W1: {=IF(OR($L$2:$N$2>60),"单边超长","正常")} -> 正常
A2: Extra Small （标准超级轻小件） | B2: Economy | C2: XY Economy Extra Small | D2: 到取货点 （PUDO） | E2: ¥3.12元+ ¥0.026/克 | F2: 26 | G2: 3.12 | H2: =IF($Q$2<=0,"请检查重量",IF($K$2>1600,"货值超渠道限制",IF($Q$2>0.5,"重量限制500G",IF($T$1="三边合计超长","三边合计超长",IF($W$1="单边超长","单边超长",ROUNDUP(F2*$Q$2+G2,2)&"元"))))) -> 请检查重量 | J2: =兴远吉尔吉斯渠道计算!O2 -> 0 | K2: =兴远吉尔吉斯渠道计算!P2 -> 0 | L2: =兴远吉尔吉斯渠道计算!Q2 -> 0 | M2: =兴远吉尔吉斯渠道计算!R2 -> 0 | N2: =兴远吉尔吉斯渠道计算!S2 -> 0 | P2: =SUM(L2:N2) -> 0 | Q2: =IF($J$2<=0,0,CEILING($J$2,0.001)) -> 0 | S2: 三边判断是否超150cm | T2: =IF($P$2>=150,"三边合计超长","正常") -> 正常 | V2: 单边判断是否超150cm | W2: {=IF(OR($L$2:$N$2>150),"单边超长","正常")} -> 正常
B3: Economy | C3: XY Economy Extra Small | D3: 到门 （Courier） | E3: ¥3.12元+ ¥0.026/克 | F3: 26 | G3: 3.12 | H3: =IF($Q$2<=0,"请检查重量",IF($K$2>1600,"货值超渠道限制",IF($Q$2>0.5,"重量限制500G",IF($T$1="三边合计超长","三边合计超长",IF($W$1="单边超长","单边超长",ROUNDUP(F3*$Q$2+G3,2)&"元"))))) -> 请检查重量 | S3: 三边判断是否超250cm | T3: =IF($P$2>=250,"三边合计超长","正常") -> 正常
B4: Standard | C4: XY Extra Small Standard | D4: 到取货点 （PUDO） | E4: ¥3,37+¥0,0393/g | F4: 39.3 | G4: 3.37 | H4: =IF($Q$2<=0,"请检查重量",IF($K$2>1600,"货值超渠道限制",IF($Q$2>0.5,"重量限制500G",IF($T$1="三边合计超长","三边合计超长",IF($W$1="单边超长","单边超长",ROUNDUP(F4*$Q$2+G4,2)&"元"))))) -> 请检查重量 | S4: 三边判断是否超310cm | T4: =IF($P$2>=310,"三边合计超长","正常") -> 正常
B5: Standard | C5: XY Extra Small Standard | D5: 到门 （Courier） | E5: ¥3,37+¥0,0393/g | F5: 39.3 | G5: 3.37 | H5: =IF($Q$2<=0,"请检查重量",IF($K$2>1600,"货值超渠道限制",IF($Q$2>0.5,"重量限制500G",IF($T$1="三边合计超长","三边合计超长",IF($W$1="单边超长","单边超长",ROUNDUP(F5*$Q$2+G5,2)&"元"))))) -> 请检查重量 | V5: 计抛渠道对比（计抛） | W5: =IF($L$2*$M$2*$N$2/12000>$Q$2,$L$2*$M$2*$N$2/12000,$Q$2) -> 0
B6: Express | C6: XY Express Extra Small | D6: 到取货点 （PUDO） | E6: ¥3元+ ¥0.045/克 | F6: 45 | G6: 3.12 | H6: =IF($Q$2<=0,"请检查重量",IF($K$2>1600,"货值超渠道限制",IF($Q$2>0.5,"重量限制500G",IF($T$1="三边合计超长","三边合计超长",IF($W$1="单边超长","单边超长",ROUNDUP(F6*$Q$2+G6,2)&"元"))))) -> 请检查重量
B7: Express | C7: XY Express Extra Small | D7: 到门 （Courier） | E7: ¥3元+ ¥0.045/克 | F7: 45 | G7: 3.12 | H7: =IF($Q$2<=0,"请检查重量",IF($K$2>1600,"货值超渠道限制",IF($Q$2>0.5,"重量限制500G",IF($T$1="三边合计超长","三边合计超长",IF($W$1="单边超长","单边超长",ROUNDUP(F7*$Q$2+G7,2)&"元"))))) -> 请检查重量
A8: Budget （标准低客单价） | B8: Economy | C8: XY Economy Budget （新） | D8: 到取货点 （PUDO） | E8: ¥23.92元+ ¥0.01768/1克 | F8: 17.68 | G8: 23.92 | H8: =IF($Q$2<=0,"请检查重量",IF($K$2>1600,"货值超渠道限制",IF($Q$2>30,"重量限制30KG",IF($Q$2<0.501,"重量不能低于501克",IF($T$2="三边合计超长","三边合计超长",IF($W$1="单边超长","单边超长",ROUNDUP(F8*$Q$2+G8,2)&"元")))))) -> 请检查重量
B9: Economy | C9: XY Economy Budget （新） | D9: 到门 （Courier） | E9: ¥23.92元+ ¥0.01768/1克 | F9: 17.68 | G9: 23.92 | H9: =IF($Q$2<=0,"请检查重量",IF($K$2>1600,"货值超渠道限制",IF($Q$2>30,"重量限制30KG",IF($Q$2<0.501,"重量不能低于501克",IF($T$2="三边合计超长","三边合计超长",IF($W$1="单边超长","单边超长",ROUNDUP(F9*$Q$2+G9,2)&"元")))))) -> 请检查重量
B10: Standard | C10: XY Standard Budget | D10: 到取货点 （PUDO） | E10: ¥23,83+¥0,0281/g | F10: 28.1 | G10: 23.83 | H10: =IF($Q$2<=0,"请检查重量",IF($K$2>1600,"货值超渠道限制",IF($Q$2>30,"重量限制30KG",IF($Q$2<0.501,"重量不能低于501克",IF($T$2="三边合计超长","三边合计超长",IF($W$1="单边超长","单边超长",ROUNDUP(F10*$Q$2+G10,2)&"元")))))) -> 请检查重量
B11: Standard | C11: XY Standard Budget | D11: 到门 （Courier） | E11: ¥23,83+¥0,0281/g | F11: 28.1 | G11: 23.83 | H11: =IF($Q$2<=0,"请检查重量",IF($K$2>1600,"货值超渠道限制",IF($Q$2>30,"重量限制30KG",IF($Q$2<0.501,"重量不能低于501克",IF($T$2="三边合计超长","三边合计超长",IF($W$1="单边超长","单边超长",ROUNDUP(F11*$Q$2+G11,2)&"元")))))) -> 请检查重量
B12: Express | C12: XY Express Budget （新） | D12: 到取货点 （PUDO） | E12: ¥23元+ ¥0.033/1克 | F12: 33 | G12: 23.92 | H12: =IF($Q$2<=0,"请检查重量",IF($K$2>1600,"货值超渠道限制",IF($Q$2>30,"重量限制30KG",IF($Q$2<0.501,"重量不能低于501克",IF($T$2="三边合计超长","三边合计超长",IF($W$1="单边超长","单边超长",ROUNDUP(F12*$Q$2+G12,2)&"元")))))) -> 请检查重量
B13: Express | C13: XY Express Budget （新） | D13: 到门 （Courier） | E13: ¥23元+ ¥0.033/1克 | F13: 33 | G13: 23.92 | H13: =IF($Q$2<=0,"请检查重量",IF($K$2>1600,"货值超渠道限制",IF($Q$2>30,"重量限制30KG",IF($Q$2<0.501,"重量不能低于501克",IF($T$2="三边合计超长","三边合计超长",IF($W$1="单边超长","单边超长",ROUNDUP(F13*$Q$2+G13,2)&"元")))))) -> 请检查重量
A14: Small （标准小件） | B14: Economy | C14: XY Economy Small | D14: 到取货点 （PUDO） | E14: ¥16.64元+ ¥0.026/克 | F14: 26 | G14: 16.64 | H14: =IF($Q$2<=0,"请检查重量",IF($K$2<1501,"货值小于渠道限制",IF($K$2>7200,"货值超渠道限制",IF($Q$2>2,"重量限制2KG",IF($T$2="三边合计超长","三边合计超长",IF($W$1="单边超长","单边超长",ROUNDUP(F14*$Q$2+G14,2)&"元")))))) -> 请检查重量
B15: Economy | C15: XY Economy Small | D15: 到门 （Courier） | E15: ¥16.64元+ ¥0.026/克 | F15: 26 | G15: 16.64 | H15: =IF($Q$2<=0,"请检查重量",IF($K$2<1501,"货值小于渠道限制",IF($K$2>7200,"货值超渠道限制",IF($Q$2>2,"重量限制2KG",IF($T$2="三边合计超长","三边合计超长",IF($W$1="单边超长","单边超长",ROUNDUP(F15*$Q$2+G15,2)&"元")))))) -> 请检查重量
B16: Standard | C16: XY Standard Small | D16: 到取货点 （PUDO） | E16: ¥17,97+¥0,0393/g | F16: 39.3 | G16: 17.97 | H16: =IF($Q$2<=0,"请检查重量",IF($K$2<1501,"货值小于渠道限制",IF($K$2>7200,"货值超渠道限制",IF($Q$2>2,"重量限制2KG",IF($T$2="三边合计超长","三边合计超长",IF($W$1="单边超长","单边超长",ROUNDUP(F16*$Q$2+G16,2)&"元")))))) -> 请检查重量
B17: Standard | C17: XY Standard Small | D17: 到门 （Courier） | E17: ¥17,97+¥0,0393/g | F17: 39.3 | G17: 17.97 | H17: =IF($Q$2<=0,"请检查重量",IF($K$2<1501,"货值小于渠道限制",IF($K$2>7200,"货值超渠道限制",IF($Q$2>2,"重量限制2KG",IF($T$2="三边合计超长","三边合计超长",IF($W$1="单边超长","单边超长",ROUNDUP(F17*$Q$2+G17,2)&"元")))))) -> 请检查重量
B18: Express | C18: XY Express Small | D18: 到取货点 （PUDO） | E18: ¥16元+ ¥0.045/克 | F18: 16 | G18: 16.64 | H18: =IF($Q$2<=0,"请检查重量",IF($K$2<1501,"货值小于渠道限制",IF($K$2>7200,"货值超渠道限制",IF($Q$2>2,"重量限制2KG",IF($T$2="三边合计超长","三边合计超长",IF($W$1="单边超长","单边超长",ROUNDUP(F18*$Q$2+G18,2)&"元")))))) -> 请检查重量
B19: Express | C19: XY Express Small | D19: 到门 （Courier） | E19: ¥16元+ ¥0.045/克 | F19: 16 | G19: 16.64 | H19: =IF($Q$2<=0,"请检查重量",IF($K$2<1501,"货值小于渠道限制",IF($K$2>7200,"货值超渠道限制",IF($Q$2>2,"重量限制2KG",IF($T$2="三边合计超长","三边合计超长",IF($W$1="单边超长","单边超长",ROUNDUP(F19*$Q$2+G19,2)&"元")))))) -> 请检查重量
A20: Big （标准大件） | B20: Economy | C20: XY Economy Big （新） | D20: 到取货点 （PUDO） | E20: ¥37.44元+ ¥0.01768/1克 | F20: 17.68 | G20: 37.44 | H20: =IF($Q$2<=0,"请检查重量",IF($K$2<1501,"货值小于渠道限制",IF($K$2>7200,"货值超渠道限制",IF($Q$2<2.001,"重量限制2001G",IF($Q$2>30,"重量限制30KG",IF($W$5>30,"体积重超30KG",IF($T$3="三边合计超长","三边合计超长",IF($W$2="单边超长","单边超长",ROUNDUP(F20*$W$5+G20,2)&"元")))))))) -> 请检查重量
B21: Economy | C21: XY Economy Big （新） | D21: 到门 （Courier） | E21: ¥37.44元+ ¥0.01768/1克 | F21: 17.68 | G21: 37.44 | H21: =IF($Q$2<=0,"请检查重量",IF($K$2<1501,"货值小于渠道限制",IF($K$2>7200,"货值超渠道限制",IF($Q$2<2.001,"重量限制2001G",IF($Q$2>30,"重量限制30KG",IF($W$5>30,"体积重超30KG",IF($T$3="三边合计超长","三边合计超长",IF($W$2="单边超长","单边超长",ROUNDUP(F21*$W$5+G21,2)&"元")))))))) -> 请检查重量
B22: Standard | C22: XY Standard Big | D22: 到取货点 （PUDO） | E22: ¥40,44+¥0,0281/g | F22: 28.1 | G22: 40.44 | H22: =IF($Q$2<=0,"请检查重量",IF($K$2<1501,"货值小于渠道限制",IF($K$2>7200,"货值超渠道限制",IF($Q$2<2.001,"重量限制2001G",IF($Q$2>30,"重量限制30KG",IF($W$5>30,"体积重超30KG",IF($T$3="三边合计超长","三边合计超长",IF($W$2="单边超长","单边超长",ROUNDUP(F22*$W$5+G22,2)&"元")))))))) -> 请检查重量
B23: Standard | C23: XY Standard Big | D23: 到门 （Courier） | E23: ¥40,44+¥0,0281/g | F23: 28.1 | G23: 40.44 | H23: =IF($Q$2<=0,"请检查重量",IF($K$2<1501,"货值小于渠道限制",IF($K$2>7200,"货值超渠道限制",IF($Q$2<2.001,"重量限制2001G",IF($Q$2>30,"重量限制30KG",IF($W$5>30,"体积重超30KG",IF($T$3="三边合计超长","三边合计超长",IF($W$2="单边超长","单边超长",ROUNDUP(F23*$W$5+G23,2)&"元")))))))) -> 请检查重量
B24: Express | C24: XY Express Big （新） | D24: 到取货点 （PUDO） | E24: ¥36元+ ¥0.033/1克 | F24: 33 | G24: 37.44 | H24: =IF($Q$2<=0,"请检查重量",IF($K$2<1501,"货值小于渠道限制",IF($K$2>7200,"货值超渠道限制",IF($Q$2<2.001,"重量限制2001G",IF($Q$2>30,"重量限制30KG",IF($W$5>30,"体积重超30KG",IF($T$3="三边合计超长","三边合计超长",IF($W$2="单边超长","单边超长",ROUNDUP(F24*$W$5+G24,2)&"元")))))))) -> 请检查重量
B25: Express | C25: XY Express Big （新） | D25: 到门 （Courier） | E25: ¥36元+ ¥0.033/1克 | F25: 33 | G25: 37.44 | H25: =IF($Q$2<=0,"请检查重量",IF($K$2<1501,"货值小于渠道限制",IF($K$2>7200,"货值超渠道限制",IF($Q$2<2.001,"重量限制2001G",IF($Q$2>30,"重量限制30KG",IF($W$5>30,"体积重超30KG",IF($T$3="三边合计超长","三边合计超长",IF($W$2="单边超长","单边超长",ROUNDUP(F25*$W$5+G25,2)&"元")))))))) -> 请检查重量
A26: XY Premium Small （高客单价小件） | B26: Economy | C26: XY Economy Premium Small | D26: 到取货点 （PUDO） | E26: ¥22.88元+ ¥0.026/克 | F26: 26 | G26: 22.88 | H26: =IF($Q$2<=0,"请检查重量",IF($K$2<7000,"货值小于渠道限制",IF($K$2>18000,"货值超渠道限制",IF($Q$2>5,"重量限制5KG",IF($T$3="三边合计超长","三边合计超长",IF($W$2="单边超长","单边超长",ROUNDUP(F26*$Q$2+G26,2)&"元")))))) -> 请检查重量
B27: Economy | C27: XY Economy Premium Small | D27: 到门 （Courier） | E27: ¥22.88元+ ¥0.026/克 | F27: 26 | G27: 22.88 | H27: =IF($Q$2<=0,"请检查重量",IF($K$2<7000,"货值小于渠道限制",IF($K$2>18000,"货值超渠道限制",IF($Q$2>5,"重量限制5KG",IF($T$3="三边合计超长","三边合计超长",IF($W$2="单边超长","单边超长",ROUNDUP(F27*$Q$2+G27,2)&"元")))))) -> 请检查重量
B28: Standard | C28: XY Standard Premium Small | D28: 到取货点 （PUDO） | E28: ¥24,71+¥0,0393/g | F28: 39.3 | G28: 24.71 | H28: =IF($Q$2<=0,"请检查重量",IF($K$2<7000,"货值小于渠道限制",IF($K$2>18000,"货值超渠道限制",IF($Q$2>5,"重量限制5KG",IF($T$3="三边合计超长","三边合计超长",IF($W$2="单边超长","单边超长",ROUNDUP(F28*$Q$2+G28,2)&"元")))))) -> 请检查重量
B29: Standard | C29: XY Standard Premium Small | D29: 到门 （Courier） | E29: ¥24,71+¥0,0393/g | F29: 39.3 | G29: 24.71 | H29: =IF($Q$2<=0,"请检查重量",IF($K$2<7000,"货值小于渠道限制",IF($K$2>18000,"货值超渠道限制",IF($Q$2>5,"重量限制5KG",IF($T$3="三边合计超长","三边合计超长",IF($W$2="单边超长","单边超长",ROUNDUP(F29*$Q$2+G29,2)&"元")))))) -> 请检查重量
B30: Express | C30: XY Express Premium Small | D30: 到取货点 （PUDO） | E30: ¥22元+ ¥0.045/克 | F30: 26 | G30: 22.88 | H30: =IF($Q$2<=0,"请检查重量",IF($K$2<7000,"货值小于渠道限制",IF($K$2>250000,"货值超渠道限制",IF($Q$2>5,"重量限制5KG",IF($T$3="三边合计超长","三边合计超长",IF($W$2="单边超长","单边超长",ROUNDUP(F30*$Q$2+G30,2)&"元")))))) -> 请检查重量
B31: Express | C31: XY Express Premium Small | D31: 到门 （Courier） | E31: ¥22元+ ¥0.045/克 | F31: 26 | G31: 22.88 | H31: =IF($Q$2<=0,"请检查重量",IF($K$2<7000,"货值小于渠道限制",IF($K$2>250000,"货值超渠道限制",IF($Q$2>5,"重量限制5KG",IF($T$3="三边合计超长","三边合计超长",IF($W$2="单边超长","单边超长",ROUNDUP(F31*$Q$2+G31,2)&"元")))))) -> 请检查重量
A32: Premium Big （高客单价大件） | B32: Economy | C32: XY Economy Premium Big （新） | D32: 到取货点 （PUDO） | E32: ¥64.48元+ ¥0.02392/1克 | F32: 23.92 | G32: 64.48 | H32: =IF($Q$2<=0,"请检查重量",IF($K$2<7000,"货值小于渠道限制",IF($K$2>18000,"货值超渠道限制",IF($Q$2<5.001,"最低限制5001G",IF($Q$2>30,"重量限制30KG",IF($W$5>30,"体积重超30KG",IF($T$4="三边合计超长","三边合计超长",IF($W$2="单边超长","单边超长",ROUNDUP(F32*$W$5+G32,2)&"元")))))))) -> 请检查重量
B33: Economy | C33: XY Economy Premium Big （新） | D33: 到门 （Courier） | E33: ¥64.48元+ ¥0.02392/1克 | F33: 23.92 | G33: 64.48 | H33: =IF($Q$2<=0,"请检查重量",IF($K$2<7000,"货值小于渠道限制",IF($K$2>18000,"货值超渠道限制",IF($Q$2<5.001,"最低限制5001G",IF($Q$2>30,"重量限制30KG",IF($W$5>30,"体积重超30KG",IF($T$4="三边合计超长","三边合计超长",IF($W$2="单边超长","单边超长",ROUNDUP(F33*$W$5+G33,2)&"元")))))))) -> 请检查重量
B34: Standard | C34: XY Standard Premium Big | D34: 到取货点 （PUDO） | E34: ¥69,64+¥0,0314/g | F34: 31.4 | G34: 69.64 | H34: =IF($Q$2<=0,"请检查重量",IF($K$2<7000,"货值小于渠道限制",IF($K$2>18000,"货值超渠道限制",IF($Q$2<5.001,"最低限制5001G",IF($Q$2>30,"重量限制30KG",IF($W$5>30,"体积重超30KG",IF($T$4="三边合计超长","三边合计超长",IF($W$2="单边超长","单边超长",ROUNDUP(F34*$W$5+G34,2)&"元")))))))) -> 请检查重量
B35: Standard | C35: XY Standard Premium Big | D35: 到门 （Courier） | E35: ¥69,64+¥0,0314/g | F35: 31.4 | G35: 69.64 | H35: =IF($Q$2<=0,"请检查重量",IF($K$2<7000,"货值小于渠道限制",IF($K$2>18000,"货值超渠道限制",IF($Q$2<5.001,"最低限制5001G",IF($Q$2>30,"重量限制30KG",IF($W$5>30,"体积重超30KG",IF($T$4="三边合计超长","三边合计超长",IF($W$2="单边超长","单边超长",ROUNDUP(F35*$W$5+G35,2)&"元")))))))) -> 请检查重量
B36: Express | C36: XY Express Premium Big （新） | D36: 到取货点 （PUDO） | E36: ¥62元+ ¥0.033/1克 | F36: 33 | G36: 64.48 | H36: =IF($Q$2<=0,"请检查重量",IF($K$2<7000,"货值小于渠道限制",IF($K$2>250000,"货值超渠道限制",IF($Q$2<5.001,"最低限制5001G",IF($Q$2>30,"重量限制30KG",IF($W$5>30,"体积重超30KG",IF($T$4="三边合计超长","三边合计超长",IF($W$2="单边超长","单边超长",ROUNDUP(F36*$W$5+G36,2)&"元")))))))) -> 请检查重量
B37: Express | C37: XY Express Premium Big （新） | D37: 到门 （Courier） | E37: ¥62元+ ¥0.033/1克 | F37: 33 | G37: 64.48 | H37: =IF($Q$2<=0,"请检查重量",IF($K$2<7000,"货值小于渠道限制",IF($K$2>250000,"货值超渠道限制",IF($Q$2<5.001,"最低限制5001G",IF($Q$2>30,"重量限制30KG",IF($W$5>30,"体积重超30KG",IF($T$4="三边合计超长","三边合计超长",IF($W$2="单边超长","单边超长",ROUNDUP(F37*$W$5+G37,2)&"元")))))))) -> 请检查重量
